pygallery/__init__.py
pygallery/__main__.py
pygallery/build.py
pygallery/main.py
pygallery/serve.py
pygallery/stars.json
pygallery/templates/album.html
pygallery/templates/photo.html
pygallery/templates/robots.txt
pygallery/templates/theme.css
pygallery-0.0.8.dist-info/licenses/LICENSE.txt
pygallery-0.0.8.dist-info/METADATA
pygallery-0.0.8.dist-info/WHEEL
pygallery-0.0.8.dist-info/entry_points.txt
pygallery-0.0.8.dist-info/top_level.txt
pygallery-0.0.8.dist-info/RECORD
