Metadata-Version: 2.4
Name: pygallery
Version: 0.0.8
Summary: Python Static Photo Gallery Generator
Author-email: David <c0d3@gpobox.net>
Maintainer-email: David <c0d3@gpobox.net>
License: Copyright (c) 2025 David
Project-URL: Homepage, https://github.com/bbc6502/pygallery
Project-URL: Bug Tracker, https://github.com/bbc6502/pygallery/issues
Keywords: photos
Classifier: Programming Language :: Python :: 3
Classifier: License :: OSI Approved :: MIT License
Classifier: Operating System :: OS Independent
Classifier: Development Status :: 3 - Alpha
Classifier: Natural Language :: English
Classifier: Operating System :: POSIX :: Linux
Classifier: Topic :: Utilities
Requires-Python: >=3.13
License-File: LICENSE.txt
Requires-Dist: jinja2
Requires-Dist: pillow
Provides-Extra: dev
Requires-Dist: wheel; extra == "dev"
Requires-Dist: build; extra == "dev"
Requires-Dist: twine; extra == "dev"
Provides-Extra: test
Requires-Dist: pytest; extra == "test"
Requires-Dist: pytest-cov; extra == "test"
Requires-Dist: coverage; extra == "test"
Dynamic: license-file
